hyperthought_transfer/__init__.py
hyperthought_transfer/antivirus/__init__.py
hyperthought_transfer/antivirus/_mcafee.py
hyperthought_transfer/antivirus/base.py
hyperthought_transfer/filebinner/__init__.py
hyperthought_transfer/filebinner/data.py
hyperthought_transfer/filebinner/database/__init__.py
hyperthought_transfer/filebinner/database/connect.py
hyperthought_transfer/filebinner/database/template/__init__.py
hyperthought_transfer/filebinner/database/template/create.py
hyperthought_transfer/filebinner/database/template/template.db
hyperthought_transfer/filebinner/process/__init__.py
hyperthought_transfer/filebinner/process/filebinner.py
hyperthought_transfer/manifest/__init__.py
hyperthought_transfer/manifest/utils.py
hyperthought_transfer/manifest/database/__init__.py
hyperthought_transfer/manifest/database/connect.py
hyperthought_transfer/manifest/database/template/__init__.py
hyperthought_transfer/manifest/database/template/create.py
hyperthought_transfer/manifest/database/template/template.db
hyperthought_transfer/manifest/processes/__init__.py
hyperthought_transfer/manifest/processes/rules.py
hyperthought_transfer-1.3.1.dist-info/LICENSE.txt
hyperthought_transfer-1.3.1.dist-info/METADATA
hyperthought_transfer-1.3.1.dist-info/WHEEL
hyperthought_transfer-1.3.1.dist-info/top_level.txt
hyperthought_transfer-1.3.1.dist-info/RECORD
