Metadata-Version: 2.1
Name: hyperthought-transfer
Version: 1.3.1
Summary: Package used to upload files to and download files from the HyperThought® content management system.
Home-page: https://github.com/pyscaffold/pyscaffold/
Author: Jason Thiese
Author-email: jthiese@ues.com
License: MIT
Project-URL: Documentation, https://pyscaffold.org/
Platform: any
Classifier: Development Status :: 4 - Beta
Classifier: Programming Language :: Python
License-File: LICENSE.txt
Requires-Dist: importlib-metadata ; python_version < "3.8"
Provides-Extra: testing
Requires-Dist: setuptools ; extra == 'testing'
Requires-Dist: pytest ; extra == 'testing'
Requires-Dist: pytest-cov ; extra == 'testing'
